neographviz/__init__.py
neographviz/app.py
neographviz/utils.py
neographviz/vis.py
neographviz/templates/index.html
neographviz/templates/typeahead.html
neographviz/templates/vis.html
neographviz-0.5.0.dist-info/LICENSE
neographviz-0.5.0.dist-info/METADATA
neographviz-0.5.0.dist-info/WHEEL
neographviz-0.5.0.dist-info/top_level.txt
neographviz-0.5.0.dist-info/RECORD
