Metadata-Version: 2.1
Name: neographviz
Version: 0.5.0
Summary: Graph display package for py2neo graphs forked from https://github.com/nicolewhite/neo4j-jupyter
Home-page: https://github.com/icfly2/neographviz
Author: Ruben Menke
Author-email: ruben.m.menke@gmail.com
License: UNKNOWN
Platform: UNKNOWN
License-File: LICENSE
Provides-Extra: app
Requires-Dist: waitress (==2.1.1) ; extra == 'app'
Requires-Dist: flask (>=1.1.1) ; extra == 'app'
